astarte/device/__init__.py
astarte/device/crypto.py
astarte/device/database.py
astarte/device/device.py
astarte/device/device_grpc.py
astarte/device/device_mqtt.py
astarte/device/exceptions.py
astarte/device/interface.py
astarte/device/introspection.py
astarte/device/mapping.py
astarte/device/pairing_handler.py
astarte_device_sdk-0.14.0.dist-info/METADATA
astarte_device_sdk-0.14.0.dist-info/WHEEL
astarte_device_sdk-0.14.0.dist-info/top_level.txt
astarte_device_sdk-0.14.0.dist-info/RECORD
